dlid/__init__.py
dlid/data.py
dlid/net.py
dlid/plotting.py
dlid/utils.py
dlid-0.1.6.dist-info/METADATA
dlid-0.1.6.dist-info/WHEEL
dlid-0.1.6.dist-info/top_level.txt
dlid-0.1.6.dist-info/RECORD
