Metadata-Version: 2.1
Name: dlid
Version: 0.1.6
Summary: My first Python library
Home-page: UNKNOWN
Author: Ivan Dolgushev
Author-email: ivandolgushev@gmail.com
License: MIT
Platform: UNKNOWN
Requires-Dist: numpy
Requires-Dist: torch
